ddnsu/__init__.py
ddnsu/__main__.py
ddnsu/main.py
ddnsu-0.1.0.dist-info/LICENSE
ddnsu-0.1.0.dist-info/METADATA
ddnsu-0.1.0.dist-info/WHEEL
ddnsu-0.1.0.dist-info/entry_points.txt
ddnsu-0.1.0.dist-info/top_level.txt
ddnsu-0.1.0.dist-info/RECORD
