Metadata-Version: 2.1
Name: ddnsu
Version: 0.1.0
Summary: A dynamic DNS update client
Author: Phillippe Ang
Maintainer: Phillippe Ang
License: Copyright (c) 2024 Phillippe Ang
Project-URL: Homepage, https://pypi.org/project/ddnsu/
Project-URL: Documentation, https://pypi.org/project/ddnsu/
Project-URL: Repository, https://github.com/phillippe/ddnsu.git
Project-URL: Issues, https://github.com/phillippe/ddnsu/issues
Project-URL: Changelog, https://github.com/phillippe/ddnsu/blob/main/CHANGELOG.md
Keywords: ddns,update,client,dynamic,dns
Classifier: Programming Language :: Python :: 3
Classifier: License :: OSI Approved :: MIT License
Requires-Python: >=3.8
License-File: LICENSE
